MsFCoppel/Base.py
MsFCoppel/ColorJson.py
MsFCoppel/ErrorMs.py
MsFCoppel/Fork.py
MsFCoppel/ForkHttp.py
MsFCoppel/HttpErrors.py
MsFCoppel/HttpResponse.py
MsFCoppel/HttpTransit.py
MsFCoppel/LogssBottle.py
MsFCoppel/MsManager.py
MsFCoppel/NatsBase.py
MsFCoppel/Util.py
MsFCoppel/Worker.py
MsFCoppel/__init__.py
MsFCoppel/http_server.py
MsFCoppel/loggs.py
MsFCoppel/loggsWrapper.py
MsFCoppel/microservices.py
MsFCoppel/ms_base.py
MsFCoppel/options.py
MsFCoppel/types.py
MsFCoppel/version_framework.py
msfcoppel_v2-2.0.1.dist-info/METADATA
msfcoppel_v2-2.0.1.dist-info/WHEEL
msfcoppel_v2-2.0.1.dist-info/top_level.txt
msfcoppel_v2-2.0.1.dist-info/RECORD
