Metadata-Version: 2.4
Name: msfcoppel_v2
Version: 2.0.1
Summary: Libreria para microservicios REST
Home-page: 
Author: Carlos Baez
Author-email: carlos.baez@coppel.com
Classifier: Programming Language :: Python :: 3
Requires-Dist: kafka-python==2.2.15
Requires-Dist: Logbook==1.9.1
Requires-Dist: asyncio-nats-client==0.10.0
Requires-Dist: jaeger-client==4.3.0
Requires-Dist: fluent-logger==0.11.1
Requires-Dist: bottle==0.13.4
Requires-Dist: coloredlogs==15.0.1
Requires-Dist: colorama==0.4.3
Requires-Dist: Pygments==2.19.2
Requires-Dist: waitress==3.0.2
Requires-Dist: redis==7.0.1
Requires-Dist: contextvars==2.4
Requires-Dist: requests==2.32.5
Requires-Dist: autodynatrace==1.0.75
Requires-Dist: opentracing==2.4.0
Dynamic: author
Dynamic: author-email
Dynamic: classifier
Dynamic: requires-dist
Dynamic: summary
